[
  {
    "title": "Build Portfolio Website",
    "description": "Need a developer to create a personal site with animations, glowing effects, and dark mode.",
    "category": "Web Development",
    "budget": 120,
    "duration": "5 Days"
  },
  {
    "title": "Design Logo for Clothing Brand",
    "description": "Looking for a logo designer experienced with fashion brands.",
    "category": "Graphic Design",
    "budget": 80,
    "duration": "3 Days"
  },
  {
    "title": "Create Promo Video",
    "description": "Need a short promo video for app launch with animation and music.",
    "category": "Video Editing",
    "budget": 150,
    "duration": "7 Days"
  },
  {
    "title": "Develop Mobile App UI",
    "description": "Design a clean and modern UI for a fitness tracking mobile app.",
    "category": "UI/UX Design",
    "budget": 200,
    "duration": "10 Days"
  },
  {
    "title": "Write SEO Articles",
    "description": "Write 10 articles optimized for SEO in the tech niche.",
    "category": "Content Writing",
    "budget": 100,
    "duration": "4 Days"
  },
  {
    "title": "Fix WordPress Bugs",
    "description": "Need a WordPress expert to resolve plugin conflicts and improve load speed.",
    "category": "Web Development",
    "budget": 90,
    "duration": "2 Days"
  },
  {
    "title": "Social Media Management",
    "description": "Manage Instagram, Twitter, and LinkedIn pages for a startup for 1 month.",
    "category": "Digital Marketing",
    "budget": 300,
    "duration": "30 Days"
  },
  {
    "title": "Build E-commerce Backend",
    "description": "Develop a scalable backend for an e-commerce site using Node.js and MongoDB.",
    "category": "Backend Development",
    "budget": 400,
    "duration": "14 Days"
  },
  {
    "title": "Translate Website to Spanish",
    "description": "Translate a complete 5-page business website from English to Spanish.",
    "category": "Translation",
    "budget": 70,
    "duration": "3 Days"
  },
  {
    "title": "Voice Over for Podcast Intro",
    "description": "Need a professional voice-over artist for a podcast intro and outro (1 min total).",
    "category": "Voice Over",
    "budget": 60,
    "duration": "2 Days"
  }
]
